examples/__init__.py
examples/TPs/__init__.py
examples/TPs/tp_vision_decouverte.py
examples/simple_scripts/WebcamVideoStream.py
examples/simple_scripts/__init__.py
examples/simple_scripts/calibrate_move.py
examples/simple_scripts/control_with_mouse.py
examples/simple_scripts/control_with_tkinter.py
examples/simple_scripts/get_pose.py
examples/simple_scripts/kinematics.py
examples/simple_scripts/little_conditionning.py
examples/simple_scripts/simple_pick_place_w_conveyor.py
examples/simple_scripts/simple_vision_pick_n_place.py
examples/simple_scripts/video_stream.py
examples/simple_scripts/workspace_creation.py
examples/vision_demonstrators/1_simple_reference_conditioning.py
examples/vision_demonstrators/2_multiple_reference_conditioning.py
examples/vision_demonstrators/3_conditioning_and_packing_2_workspaces.py
examples/vision_demonstrators/4_conditionning_with_conveyor.py
examples/vision_demonstrators/__init__.py
pyniryo/__init__.py
pyniryo/version.py
pyniryo/api/__init__.py
pyniryo/api/communication_functions.py
pyniryo/api/enums_communication.py
pyniryo/api/exceptions.py
pyniryo/api/objects.py
pyniryo/api/tcp_client.py
pyniryo/utils/__init__.py
pyniryo/utils/logging.py
pyniryo/vision/__init__.py
pyniryo/vision/enums.py
pyniryo/vision/image_functions.py
pyniryo/vision/markers_detection.py
pyniryo/vision/math_functions.py
pyniryo-1.2.1.dist-info/LICENSE
pyniryo-1.2.1.dist-info/METADATA
pyniryo-1.2.1.dist-info/WHEEL
pyniryo-1.2.1.dist-info/top_level.txt
pyniryo-1.2.1.dist-info/RECORD
