Metadata-Version: 2.1
Name: pyniryo
Version: 1.2.1
Summary: Package to control Niryo Robot "Ned" through TCP
Home-page: https://github.com/NiryoRobotics/pyniryo
Author: Niryo
Author-email: r.lux@niryo.com
Maintainer: Niryo
Maintainer-email: admin.it@niryo.com
License: GNU 3.0
Classifier: Development Status :: 5 - Production/Stable
Classifier: Intended Audience :: Developers
Classifier: Intended Audience :: Education
Classifier: Intended Audience :: Science/Research
Classifier: License :: OSI Approved :: GNU General Public License v3 (GPLv3)
Classifier: Natural Language :: English
Classifier: Operating System :: OS Independent
Classifier: Programming Language :: Python :: 2.7
Classifier: Programming Language :: Python :: 3.5
Classifier: Programming Language :: Python :: 3.6
Classifier: Programming Language :: Python :: 3.7
Classifier: Programming Language :: Python :: 3.8
Classifier: Programming Language :: Python :: 3.9
Classifier: Programming Language :: Python :: 3.10
Classifier: Programming Language :: Python :: 3.11
Classifier: Topic :: Scientific/Engineering :: Artificial Intelligence
Classifier: Topic :: Scientific/Engineering :: Image Recognition
Classifier: Topic :: Scientific/Engineering :: Human Machine Interfaces
License-File: LICENSE
Requires-Dist: enum34
Requires-Dist: typing-extensions
Requires-Dist: opencv-python<=4.2.0.32; python_version == "2.7"
Requires-Dist: opencv-python>=4.3.0.38; python_version > "2.7"
